{
  "period": {
    "start": "2026-05-10",
    "end": "2026-05-10"
  },
  "generated_at": "2026-05-11T13:49:04.841453",
  "totals": {
    "spend": 229.46,
    "conversations": 26,
    "cpa": 8.83,
    "reach": 20644,
    "impressions": 30910,
    "clicks": 158,
    "profile_visits": 99,
    "ads_count": 39,
    "active_ads": 39
  },
  "ads": [
    {
      "name": "Ad 00 - REELS - R$1,00 - BELÉM - COMO QUE UMA ARMAÇÃO",
      "ad_id": "120240085213630661",
      "city": "BELÉM",
      "offer": "R$ 1,00",
      "hook": "COMO QUE UMA ARMAÇÃO",
      "status": "ATIVO",
      "spend": 14.48,
      "conversations": 3,
      "cpa": 4.83,
      "clicks": 10,
      "ctr": 0.0122,
      "reach": 654,
      "impressions": 818,
      "profile_visits": 5,
      "preview_url": "https://fb.me/2rc0wD6RMPK03Eb"
    },
    {
      "name": "Ad - 00 - REELS - R$1,00 - CASTANHAL - VALOR MEGA ACESSÍVEL",
      "ad_id": "120240910668780661",
      "city": "CASTANHAL",
      "offer": "R$ 1,00",
      "hook": "VALOR MEGA ACESSÍVEL",
      "status": "ATIVO",
      "spend": 12.95,
      "conversations": 3,
      "cpa": 4.32,
      "clicks": 12,
      "ctr": 0.6522,
      "reach": 1414,
      "impressions": 1840,
      "profile_visits": 5,
      "preview_url": "https://fb.me/1Qsz5WylIerWPYq"
    },
    {
      "name": "Ad 01 - REELS - MULTIFOCAL - CASTANHAL",
      "ad_id": "120240932538580661",
      "city": "CASTANHAL",
      "offer": "MULTIFOCAL",
      "hook": "MULTIFOCAL",
      "status": "ATIVO",
      "spend": 8.25,
      "conversations": 0,
      "cpa": 0.0,
      "clicks": 4,
      "ctr": 0.5952,
      "reach": 498,
      "impressions": 672,
      "profile_visits": 4,
      "preview_url": "https://fb.me/2W7BkQlxpVrgzHg"
    },
    {
      "name": "Ad 00 - REELS - LIGAÇÃO - ANANINDEUA - ALERTA URGENTE",
      "ad_id": "120241114926950661",
      "city": "ANANINDEUA",
      "offer": "LIGAÇÃO",
      "hook": "ALERTA URGENTE",
      "status": "ATIVO",
      "spend": 10.54,
      "conversations": 1,
      "cpa": 10.54,
      "clicks": 2,
      "ctr": 0.3521,
      "reach": 473,
      "impressions": 568,
      "profile_visits": 2,
      "preview_url": "https://fb.me/1QYq4sUIAT46PVt"
    },
    {
      "name": "Ad 02 - REELS - MULTIFOCAL - CASTANHAL - MAIS DE 40",
      "ad_id": "120243469952010661",
      "city": "CASTANHAL",
      "offer": "MULTIFOCAL",
      "hook": "MULTIFOCAL",
      "status": "ATIVO",
      "spend": 0.06,
      "conversations": 0,
      "cpa": 0.0,
      "clicks": 0,
      "ctr": 0.0,
      "reach": 9,
      "impressions": 11,
      "profile_visits": 0,
      "preview_url": "https://fb.me/1TgdJkAxTfbmfbb"
    },
    {
      "name": "Ad 01 - REELS - LIGAÇÃO - BELÉM",
      "ad_id": "120243854846880661",
      "city": "BELÉM",
      "offer": "LIGAÇÃO",
      "hook": "LIGAÇÃO",
      "status": "ATIVO",
      "spend": 12.73,
      "conversations": 4,
      "cpa": 3.18,
      "clicks": 9,
      "ctr": 0.0121,
      "reach": 580,
      "impressions": 746,
      "profile_visits": 4,
      "preview_url": "https://fb.me/1SMAkNYDmDxPKRG"
    },
    {
      "name": "Ad 01 - REELS - DOBRO - ANANINDEUA - RESULTADO EM DOBRO",
      "ad_id": "120243912680300661",
      "city": "ANANINDEUA",
      "offer": "EM DOBRO",
      "hook": "DOBRO",
      "status": "ATIVO",
      "spend": 0.03,
      "conversations": 0,
      "cpa": 0.0,
      "clicks": 0,
      "ctr": 0.0,
      "reach": 4,
      "impressions": 4,
      "profile_visits": 0,
      "preview_url": "https://fb.me/1TrOipBZy3ayZJU"
    },
    {
      "name": "Ad 00 - REELS - DOBRO - ANANINDEUA - OLHA SÓ ISSO",
      "ad_id": "120243912680310661",
      "city": "ANANINDEUA",
      "offer": "EM DOBRO",
      "hook": "DOBRO",
      "status": "ATIVO",
      "spend": 0.22,
      "conversations": 0,
      "cpa": 0.0,
      "clicks": 0,
      "ctr": 0.0,
      "reach": 12,
      "impressions": 16,
      "profile_visits": 0,
      "preview_url": "https://fb.me/1TqkVmBtkPA5FIf"
    },
    {
      "name": "Ad 02 - REELS - DOBRO - ANANINDEUA - SEU ÓCULOS VALE DOIS",
      "ad_id": "120243912828060661",
      "city": "ANANINDEUA",
      "offer": "EM DOBRO",
      "hook": "DOBRO",
      "status": "ATIVO",
      "spend": 14.25,
      "conversations": 0,
      "cpa": 0.0,
      "clicks": 3,
      "ctr": 0.3175,
      "reach": 757,
      "impressions": 945,
      "profile_visits": 5,
      "preview_url": "https://fb.me/2ogPAImYX4hu3RI"
    },
    {
      "name": "Ad 01 - REELS - MULTIFOCAL HOYA - ANANINDEUA - OLHA O TANTO DE HOYA",
      "ad_id": "120244460224100661",
      "city": "ANANINDEUA",
      "offer": "MULTIFOCAL",
      "hook": "MULTIFOCAL",
      "status": "ATIVO",
      "spend": 8.02,
      "conversations": 0,
      "cpa": 0.0,
      "clicks": 3,
      "ctr": 0.7109,
      "reach": 353,
      "impressions": 422,
      "profile_visits": 1,
      "preview_url": "https://fb.me/21B6s9q7UJHCr3y"
    },
    {
      "name": "Ad 04 - REELS - AQUECIMENTO - BELÉM",
      "ad_id": "120244467502430661",
      "city": "BELÉM",
      "offer": "AQUECIMENTO",
      "hook": "OUTRO",
      "status": "ATIVO",
      "spend": 11.38,
      "conversations": 1,
      "cpa": 11.38,
      "clicks": 12,
      "ctr": 0.2651,
      "reach": 2239,
      "impressions": 4526,
      "profile_visits": 6,
      "preview_url": "https://fb.me/1U6aT4sH3xZAcaB"
    },
    {
      "name": "Ad 05 - REELS - AQUECIMENTO - BELÉM — Cópia",
      "ad_id": "120244467534970661",
      "city": "BELÉM",
      "offer": "AQUECIMENTO",
      "hook": "OUTRO",
      "status": "ATIVO",
      "spend": 0.03,
      "conversations": 0,
      "cpa": 0.0,
      "clicks": 0,
      "ctr": 0.0,
      "reach": 17,
      "impressions": 17,
      "profile_visits": 0,
      "preview_url": "https://fb.me/1U1RST1R0GjnTrv"
    },
    {
      "name": "Ad 06 - REELS - AQUECIMENTO - BELÉM",
      "ad_id": "120244467588340661",
      "city": "BELÉM",
      "offer": "AQUECIMENTO",
      "hook": "OUTRO",
      "status": "ATIVO",
      "spend": 0.12,
      "conversations": 0,
      "cpa": 0.0,
      "clicks": 0,
      "ctr": 0.0,
      "reach": 46,
      "impressions": 50,
      "profile_visits": 0,
      "preview_url": "https://fb.me/1TvItU7eHwqoYnw"
    },
    {
      "name": "Ad 04 - REELS - AQUECIMENTO - CASTANHAL",
      "ad_id": "120244467648210661",
      "city": "CASTANHAL",
      "offer": "AQUECIMENTO",
      "hook": "OUTRO",
      "status": "ATIVO",
      "spend": 3.06,
      "conversations": 0,
      "cpa": 0.0,
      "clicks": 0,
      "ctr": 0.0,
      "reach": 846,
      "impressions": 1264,
      "profile_visits": 1,
      "preview_url": "https://fb.me/2uXDae8M1UMNPLJ"
    },
    {
      "name": "Ad 05 - REELS - AQUECIMENTO - CASTANHAL",
      "ad_id": "120244467698500661",
      "city": "CASTANHAL",
      "offer": "AQUECIMENTO",
      "hook": "OUTRO",
      "status": "ATIVO",
      "spend": 1.67,
      "conversations": 0,
      "cpa": 0.0,
      "clicks": 0,
      "ctr": 0.0,
      "reach": 600,
      "impressions": 705,
      "profile_visits": 1,
      "preview_url": "https://fb.me/1QmqVtI8BM8aBFn"
    },
    {
      "name": "Ad 06 - REELS - AQUECIMENTO - CASTANHAL",
      "ad_id": "120244467720240661",
      "city": "CASTANHAL",
      "offer": "AQUECIMENTO",
      "hook": "OUTRO",
      "status": "ATIVO",
      "spend": 6.66,
      "conversations": 0,
      "cpa": 0.0,
      "clicks": 4,
      "ctr": 0.1387,
      "reach": 1728,
      "impressions": 2884,
      "profile_visits": 4,
      "preview_url": "https://fb.me/1RHSyoi1iwJdNG4"
    },
    {
      "name": "Ad 06 - REELS - AQUECIMENTO - ANANINDEUA",
      "ad_id": "120244467780970661",
      "city": "ANANINDEUA",
      "offer": "AQUECIMENTO",
      "hook": "OUTRO",
      "status": "ATIVO",
      "spend": 11.88,
      "conversations": 0,
      "cpa": 0.0,
      "clicks": 10,
      "ctr": 0.2695,
      "reach": 1823,
      "impressions": 3711,
      "profile_visits": 3,
      "preview_url": "https://fb.me/24GbicWuEZbsjaN"
    },
    {
      "name": "Ad 06 - REELS - AQUECIMENTO - CAPANEMA",
      "ad_id": "120244467808760661",
      "city": "CAPANEMA",
      "offer": "AQUECIMENTO",
      "hook": "OUTRO",
      "status": "ATIVO",
      "spend": 11.23,
      "conversations": 0,
      "cpa": 0.0,
      "clicks": 11,
      "ctr": 0.3847,
      "reach": 1000,
      "impressions": 2859,
      "profile_visits": 5,
      "preview_url": "https://fb.me/2aMTshMUsR778k3"
    },
    {
      "name": "Ad 07 - REELS - AQUECIMENTO - CAPANEMA",
      "ad_id": "120244467857610661",
      "city": "CAPANEMA",
      "offer": "AQUECIMENTO",
      "hook": "OUTRO",
      "status": "ATIVO",
      "spend": 0.52,
      "conversations": 0,
      "cpa": 0.0,
      "clicks": 0,
      "ctr": 0.0,
      "reach": 131,
      "impressions": 154,
      "profile_visits": 0,
      "preview_url": "https://fb.me/27FFpZvlMkKDWob"
    },
    {
      "name": "Ad 01 - REELS - DOBRO - CASTANHAL —  RESULTADO EM DOBRO",
      "ad_id": "120244628219760661",
      "city": "CASTANHAL",
      "offer": "EM DOBRO",
      "hook": "DOBRO",
      "status": "ATIVO",
      "spend": 0.02,
      "conversations": 0,
      "cpa": 0.0,
      "clicks": 0,
      "ctr": 0.0,
      "reach": 3,
      "impressions": 3,
      "profile_visits": 0,
      "preview_url": "https://fb.me/1TgikN9nj04Nees"
    },
    {
      "name": "Ad 00 - REELS - DOBRO - CASTANHAL — ÓCULOS ACETATO",
      "ad_id": "120244628219770661",
      "city": "CASTANHAL",
      "offer": "EM DOBRO",
      "hook": "DOBRO",
      "status": "ATIVO",
      "spend": 6.51,
      "conversations": 0,
      "cpa": 0.0,
      "clicks": 4,
      "ctr": 0.6309,
      "reach": 557,
      "impressions": 634,
      "profile_visits": 2,
      "preview_url": "https://fb.me/1TzM6m3Z1Pgqw2q"
    },
    {
      "name": "Ad 01 - REELS - DOBRO - CASTANHAL —  RESULTADO EM DOBRO",
      "ad_id": "120244629429800661",
      "city": "CASTANHAL",
      "offer": "EM DOBRO",
      "hook": "DOBRO",
      "status": "ATIVO",
      "spend": 0.38,
      "conversations": 0,
      "cpa": 0.0,
      "clicks": 0,
      "ctr": 0.0,
      "reach": 46,
      "impressions": 47,
      "profile_visits": 0,
      "preview_url": "https://fb.me/2efQYuK11RtI7m4"
    },
    {
      "name": "Ad 00 - REELS - DOBRO - CASTANHAL — ÓCULOS ACETATO",
      "ad_id": "120244629429820661",
      "city": "CASTANHAL",
      "offer": "EM DOBRO",
      "hook": "DOBRO",
      "status": "ATIVO",
      "spend": 6.77,
      "conversations": 0,
      "cpa": 0.0,
      "clicks": 4,
      "ctr": 0.6231,
      "reach": 533,
      "impressions": 642,
      "profile_visits": 5,
      "preview_url": "https://fb.me/27UNxvWRauJDV88"
    },
    {
      "name": "Ad 00 - REELS - DOBRO - BELÉM — ÓCULOS ACETATO",
      "ad_id": "120244629769090661",
      "city": "BELÉM",
      "offer": "EM DOBRO",
      "hook": "DOBRO",
      "status": "ATIVO",
      "spend": 7.76,
      "conversations": 0,
      "cpa": 0.0,
      "clicks": 3,
      "ctr": 0.7958,
      "reach": 350,
      "impressions": 377,
      "profile_visits": 4,
      "preview_url": "https://fb.me/28XviznoQuxwWMJ"
    },
    {
      "name": "Ad 01 - REELS - DOBRO - BELÉM —  RESULTADO EM DOBRO",
      "ad_id": "120244631058380661",
      "city": "BELÉM",
      "offer": "EM DOBRO",
      "hook": "DOBRO",
      "status": "ATIVO",
      "spend": 0.47,
      "conversations": 0,
      "cpa": 0.0,
      "clicks": 0,
      "ctr": 0.0,
      "reach": 23,
      "impressions": 25,
      "profile_visits": 0,
      "preview_url": "https://fb.me/1WHnyjPESEVcaGL"
    },
    {
      "name": "Ad 00 - REELS - DOBRO - BELÉM — ÓCULOS ACETATO",
      "ad_id": "120244631058400661",
      "city": "BELÉM",
      "offer": "EM DOBRO",
      "hook": "DOBRO",
      "status": "ATIVO",
      "spend": 6.98,
      "conversations": 0,
      "cpa": 0.0,
      "clicks": 2,
      "ctr": 0.6803,
      "reach": 280,
      "impressions": 294,
      "profile_visits": 2,
      "preview_url": "https://fb.me/2obV67AGja5PRAm"
    },
    {
      "name": "Ad 01 - REELS - R$1,00 - ANANINDEUA —  MODELO HEXAGONAL",
      "ad_id": "120244631209620661",
      "city": "ANANINDEUA",
      "offer": "R$ 1,00",
      "hook": "OUTRO",
      "status": "ATIVO",
      "spend": 7.77,
      "conversations": 3,
      "cpa": 2.59,
      "clicks": 5,
      "ctr": 0.996,
      "reach": 479,
      "impressions": 502,
      "profile_visits": 4,
      "preview_url": "https://fb.me/2go6RcEU3yUJ4C8"
    },
    {
      "name": "Ad 01 - REELS - R$1,00 - BELÉM — ALGUÉM ME ELOGIA",
      "ad_id": "120244631209700661",
      "city": "BELÉM",
      "offer": "R$ 1,00",
      "hook": "OUTRO",
      "status": "ATIVO",
      "spend": 8.42,
      "conversations": 1,
      "cpa": 8.42,
      "clicks": 4,
      "ctr": 0.011,
      "reach": 350,
      "impressions": 365,
      "profile_visits": 2,
      "preview_url": "https://fb.me/BeCvMZPA6dK7P6z"
    },
    {
      "name": "Ad - 00 - REELS - R$1,00 - CASTANHAL - VALOR MEGA ACESSÍVEL",
      "ad_id": "120245094813260661",
      "city": "CASTANHAL",
      "offer": "R$ 1,00",
      "hook": "VALOR MEGA ACESSÍVEL",
      "status": "ATIVO",
      "spend": 8.56,
      "conversations": 2,
      "cpa": 4.28,
      "clicks": 3,
      "ctr": 0.2465,
      "reach": 972,
      "impressions": 1217,
      "profile_visits": 4,
      "preview_url": "https://fb.me/2k4flJbSR7bl3bs"
    },
    {
      "name": "Ad 00 - REELS - R$1,00 - ANANINDEUA —  NA MÃO UM REAL",
      "ad_id": "120245101029690661",
      "city": "ANANINDEUA",
      "offer": "R$ 1,00",
      "hook": "OUTRO",
      "status": "ATIVO",
      "spend": 7.66,
      "conversations": 1,
      "cpa": 7.66,
      "clicks": 11,
      "ctr": 0.0101,
      "reach": 1013,
      "impressions": 1093,
      "profile_visits": 6,
      "preview_url": "https://fb.me/25ZN2rjjUyGzvHI"
    },
    {
      "name": "Ad 00 - REELS - R$1,00 - ANANINDEUA —  NA MÃO UM REAL",
      "ad_id": "120245101586720661",
      "city": "ANANINDEUA",
      "offer": "R$ 1,00",
      "hook": "OUTRO",
      "status": "ATIVO",
      "spend": 8.21,
      "conversations": 1,
      "cpa": 8.21,
      "clicks": 4,
      "ctr": 0.5618,
      "reach": 634,
      "impressions": 712,
      "profile_visits": 1,
      "preview_url": "https://fb.me/1TWts8zFTtMjYzt"
    },
    {
      "name": "Ad 00 - REELS - MULTIFOCAL - CASTANHAL - AFASTANDO O CELULAR",
      "ad_id": "120245344151220661",
      "city": "CASTANHAL",
      "offer": "MULTIFOCAL",
      "hook": "MULTIFOCAL",
      "status": "ATIVO",
      "spend": 6.37,
      "conversations": 0,
      "cpa": 0.0,
      "clicks": 6,
      "ctr": 0.9772,
      "reach": 451,
      "impressions": 614,
      "profile_visits": 4,
      "preview_url": "https://fb.me/28vRE3voqBxfpRP"
    },
    {
      "name": "Ad 00 - REELS - DOBRO - CASTANHAL — FAZ UM E LEVA DOIS",
      "ad_id": "120245345287850661",
      "city": "CASTANHAL",
      "offer": "EM DOBRO",
      "hook": "DOBRO",
      "status": "ATIVO",
      "spend": 1.35,
      "conversations": 0,
      "cpa": 0.0,
      "clicks": 4,
      "ctr": 0.0248,
      "reach": 145,
      "impressions": 161,
      "profile_visits": 2,
      "preview_url": "https://fb.me/2fBoesHlZj5aQuU"
    },
    {
      "name": "Ad 00 - REELS - DOBRO - BELÉM - FAZ UM E LEVA DOIS",
      "ad_id": "120245345878320661",
      "city": "BELÉM",
      "offer": "EM DOBRO",
      "hook": "DOBRO",
      "status": "ATIVO",
      "spend": 6.14,
      "conversations": 1,
      "cpa": 6.14,
      "clicks": 6,
      "ctr": 0.0115,
      "reach": 431,
      "impressions": 521,
      "profile_visits": 5,
      "preview_url": "https://fb.me/2udWMbM5ZaAEKPJ"
    },
    {
      "name": "Ad 00 - REELS - MULTIFOCAL - BELÉM - AFASTANDO O CELULAR",
      "ad_id": "120245346372520661",
      "city": "BELÉM",
      "offer": "MULTIFOCAL",
      "hook": "MULTIFOCAL",
      "status": "ATIVO",
      "spend": 0.08,
      "conversations": 0,
      "cpa": 0.0,
      "clicks": 0,
      "ctr": 0.0,
      "reach": 7,
      "impressions": 7,
      "profile_visits": 0,
      "preview_url": "https://fb.me/2dBRZwCH7SxhSJQ"
    },
    {
      "name": "Ad 01 - REELS - MULTIFOCAL - BELÉM - MULTIFOCAL DO JEITO CERTO",
      "ad_id": "120245346372530661",
      "city": "BELÉM",
      "offer": "MULTIFOCAL",
      "hook": "MULTIFOCAL",
      "status": "ATIVO",
      "spend": 6.96,
      "conversations": 0,
      "cpa": 0.0,
      "clicks": 4,
      "ctr": 0.0109,
      "reach": 298,
      "impressions": 367,
      "profile_visits": 4,
      "preview_url": "https://fb.me/2KNhdhb7P8WVNB1"
    },
    {
      "name": "Ad 01 - REELS - DOBRO - ANANINDEUA - MESMO GRAU E QUALIDADE",
      "ad_id": "120245346970210661",
      "city": "ANANINDEUA",
      "offer": "EM DOBRO",
      "hook": "DOBRO",
      "status": "ATIVO",
      "spend": 0.08,
      "conversations": 0,
      "cpa": 0.0,
      "clicks": 0,
      "ctr": 0.0,
      "reach": 8,
      "impressions": 8,
      "profile_visits": 0,
      "preview_url": "https://fb.me/2gU8NNLVbjXueIk"
    },
    {
      "name": "Ad 00 - REELS - DOBRO - ANANINDEUA - FAZ UM E LEVA DOIS",
      "ad_id": "120245346970220661",
      "city": "ANANINDEUA",
      "offer": "EM DOBRO",
      "hook": "DOBRO",
      "status": "ATIVO",
      "spend": 5.92,
      "conversations": 0,
      "cpa": 0.0,
      "clicks": 5,
      "ctr": 0.774,
      "reach": 560,
      "impressions": 646,
      "profile_visits": 2,
      "preview_url": "https://fb.me/2p4Czy4gUQijbBT"
    },
    {
      "name": "Ad - 00 - REELS - VAGA",
      "ad_id": "120245486943470661",
      "city": "OUTRO",
      "offer": "OUTRO",
      "hook": "OUTRO",
      "status": "ATIVO",
      "spend": 4.97,
      "conversations": 5,
      "cpa": 0.99,
      "clicks": 13,
      "ctr": 0.0281,
      "reach": 320,
      "impressions": 463,
      "profile_visits": 6,
      "preview_url": "https://fb.me/2WX3pESuYZRIkoX"
    }
  ]
}