{
  "period": {
    "start": "2026-04-27",
    "end": "2026-04-27"
  },
  "generated_at": "2026-04-28T12:24:58.619936",
  "totals": {
    "spend": 453.07,
    "conversations": 43,
    "cpa": 10.54,
    "reach": 29305,
    "impressions": 41274,
    "clicks": 218,
    "profile_visits": 5564,
    "ads_count": 42,
    "active_ads": 42
  },
  "ads": [
    {
      "name": "Ad - 00 - REELS - LIGAÇÃO - BELÉM",
      "ad_id": "120231674213550661",
      "city": "BELÉM",
      "offer": "LIGAÇÃO",
      "hook": "LIGAÇÃO",
      "status": "ATIVO",
      "spend": 18.44,
      "conversations": 2,
      "cpa": 9.22,
      "clicks": 11,
      "ctr": 0.9039,
      "reach": 817,
      "impressions": 1217,
      "profile_visits": 174,
      "preview_url": "https://fb.me/2716NcXLcdWtIVg"
    },
    {
      "name": "Ad 00 - REELS - R$1,00 - BELÉM - COMO QUE UMA ARMAÇÃO",
      "ad_id": "120240085213630661",
      "city": "BELÉM",
      "offer": "R$ 1,00",
      "hook": "COMO QUE UMA ARMAÇÃO",
      "status": "ATIVO",
      "spend": 12.16,
      "conversations": 1,
      "cpa": 12.16,
      "clicks": 6,
      "ctr": 0.0113,
      "reach": 430,
      "impressions": 531,
      "profile_visits": 89,
      "preview_url": "https://fb.me/212nEbcEjgtSiOy"
    },
    {
      "name": "Ad 00 - REELS - EXAME DE VISTA - BELÉM",
      "ad_id": "120240085912880661",
      "city": "BELÉM",
      "offer": "EXAME DE VISTA",
      "hook": "EXAME DE VISTA",
      "status": "ATIVO",
      "spend": 10.91,
      "conversations": 1,
      "cpa": 10.91,
      "clicks": 5,
      "ctr": 0.6596,
      "reach": 660,
      "impressions": 758,
      "profile_visits": 141,
      "preview_url": "https://fb.me/1S5508T3zHdtoiS"
    },
    {
      "name": "Ad 01 - REELS - EXAME DE VISTA - CAPANEMA",
      "ad_id": "120240630519500661",
      "city": "CAPANEMA",
      "offer": "EXAME DE VISTA",
      "hook": "EXAME DE VISTA",
      "status": "ATIVO",
      "spend": 14.75,
      "conversations": 1,
      "cpa": 14.75,
      "clicks": 5,
      "ctr": 0.261,
      "reach": 1460,
      "impressions": 1916,
      "profile_visits": 241,
      "preview_url": "https://fb.me/1Z1ZeOBoveoKwge"
    },
    {
      "name": "Ad 01 - REELS - EXAME DE VISTA - BELÉM",
      "ad_id": "120240631952700661",
      "city": "BELÉM",
      "offer": "EXAME DE VISTA",
      "hook": "EXAME DE VISTA",
      "status": "ATIVO",
      "spend": 4.03,
      "conversations": 0,
      "cpa": 0.0,
      "clicks": 4,
      "ctr": 0.0172,
      "reach": 194,
      "impressions": 233,
      "profile_visits": 33,
      "preview_url": "https://fb.me/2cSzy9VWLwZtgsi"
    },
    {
      "name": "Ad - 00 - REELS - R$1,00 - CASTANHAL - VALOR MEGA ACESSÍVEL",
      "ad_id": "120240910668780661",
      "city": "CASTANHAL",
      "offer": "R$ 1,00",
      "hook": "VALOR MEGA ACESSÍVEL",
      "status": "ATIVO",
      "spend": 25.65,
      "conversations": 3,
      "cpa": 8.55,
      "clicks": 10,
      "ctr": 0.386,
      "reach": 2057,
      "impressions": 2591,
      "profile_visits": 372,
      "preview_url": "https://fb.me/1UYK9tMlYpQWdQr"
    },
    {
      "name": "Ad 00 - REELS - R$1,00 - ANANINDEUA - COMO QUE UMA ARMAÇÃO",
      "ad_id": "120240911837010661",
      "city": "ANANINDEUA",
      "offer": "R$ 1,00",
      "hook": "COMO QUE UMA ARMAÇÃO",
      "status": "ATIVO",
      "spend": 17.81,
      "conversations": 6,
      "cpa": 2.97,
      "clicks": 10,
      "ctr": 0.7092,
      "reach": 1269,
      "impressions": 1410,
      "profile_visits": 285,
      "preview_url": "https://fb.me/1MEbI5qdGgWKhYb"
    },
    {
      "name": "Ad 01 - REELS - MULTIFOCAL - CASTANHAL",
      "ad_id": "120240932538580661",
      "city": "CASTANHAL",
      "offer": "MULTIFOCAL",
      "hook": "MULTIFOCAL",
      "status": "ATIVO",
      "spend": 10.66,
      "conversations": 0,
      "cpa": 0.0,
      "clicks": 7,
      "ctr": 0.9929,
      "reach": 506,
      "impressions": 705,
      "profile_visits": 135,
      "preview_url": "https://fb.me/29YRjWOzXNGbh4D"
    },
    {
      "name": "Ad 00 - REELS - LIGAÇÃO - ANANINDEUA - ALERTA URGENTE",
      "ad_id": "120241114926950661",
      "city": "ANANINDEUA",
      "offer": "LIGAÇÃO",
      "hook": "ALERTA URGENTE",
      "status": "ATIVO",
      "spend": 19.4,
      "conversations": 3,
      "cpa": 6.47,
      "clicks": 8,
      "ctr": 0.7105,
      "reach": 900,
      "impressions": 1126,
      "profile_visits": 271,
      "preview_url": "https://fb.me/205P1BZG69BtvQk"
    },
    {
      "name": "Ad 01 - REELS - LIGAÇÃO - BELÉM",
      "ad_id": "120243854846880661",
      "city": "BELÉM",
      "offer": "LIGAÇÃO",
      "hook": "LIGAÇÃO",
      "status": "ATIVO",
      "spend": 25.76,
      "conversations": 5,
      "cpa": 5.15,
      "clicks": 10,
      "ctr": 0.8929,
      "reach": 959,
      "impressions": 1120,
      "profile_visits": 314,
      "preview_url": "https://fb.me/1OM6pXCC4538fst"
    },
    {
      "name": "Ad 01 - REELS - DOBRO - CASTANHAL —  RESULTADO EM DOBRO",
      "ad_id": "120243912085090661",
      "city": "CASTANHAL",
      "offer": "EM DOBRO",
      "hook": "DOBRO",
      "status": "ATIVO",
      "spend": 19.72,
      "conversations": 2,
      "cpa": 9.86,
      "clicks": 9,
      "ctr": 0.5566,
      "reach": 1064,
      "impressions": 1617,
      "profile_visits": 225,
      "preview_url": "https://fb.me/1TybLtink8KkgxX"
    },
    {
      "name": "Ad 01 - REELS - DOBRO - ANANINDEUA - RESULTADO EM DOBRO",
      "ad_id": "120243912680300661",
      "city": "ANANINDEUA",
      "offer": "EM DOBRO",
      "hook": "DOBRO",
      "status": "ATIVO",
      "spend": 0.43,
      "conversations": 0,
      "cpa": 0.0,
      "clicks": 0,
      "ctr": 0.0,
      "reach": 41,
      "impressions": 48,
      "profile_visits": 14,
      "preview_url": "https://fb.me/1Osc8VVUHwYBpy8"
    },
    {
      "name": "Ad 02 - REELS - DOBRO - ANANINDEUA - SEU ÓCULOS VALE DOIS",
      "ad_id": "120243912828060661",
      "city": "ANANINDEUA",
      "offer": "EM DOBRO",
      "hook": "DOBRO",
      "status": "ATIVO",
      "spend": 17.52,
      "conversations": 1,
      "cpa": 17.52,
      "clicks": 7,
      "ctr": 0.7392,
      "reach": 751,
      "impressions": 947,
      "profile_visits": 146,
      "preview_url": "https://fb.me/24dpy5501Nt1zwB"
    },
    {
      "name": "Ad 00 - REELS - DOBRO - BELÉM — RESULTADO EM DOBRO",
      "ad_id": "120243913075040661",
      "city": "BELÉM",
      "offer": "EM DOBRO",
      "hook": "DOBRO",
      "status": "ATIVO",
      "spend": 21.92,
      "conversations": 2,
      "cpa": 10.96,
      "clicks": 14,
      "ctr": 0.0152,
      "reach": 717,
      "impressions": 919,
      "profile_visits": 238,
      "preview_url": "https://fb.me/3663Zdp8fG6WOF6"
    },
    {
      "name": "Ad 01 - REELS - MULTIFOCAL HOYA - ANANINDEUA - OLHA O TANTO DE HOYA",
      "ad_id": "120244460224100661",
      "city": "ANANINDEUA",
      "offer": "MULTIFOCAL",
      "hook": "MULTIFOCAL",
      "status": "ATIVO",
      "spend": 12.62,
      "conversations": 1,
      "cpa": 12.62,
      "clicks": 7,
      "ctr": 0.0114,
      "reach": 498,
      "impressions": 613,
      "profile_visits": 135,
      "preview_url": "https://fb.me/23C1skgG06jeblP"
    },
    {
      "name": "Ad 01 - REELS - MULTIFOCAL HOYA - BELÉM - NÃO DEVERIA FALAR ISSO",
      "ad_id": "120244460493110661",
      "city": "BELÉM",
      "offer": "MULTIFOCAL",
      "hook": "MULTIFOCAL",
      "status": "ATIVO",
      "spend": 8.34,
      "conversations": 2,
      "cpa": 4.17,
      "clicks": 4,
      "ctr": 0.9804,
      "reach": 327,
      "impressions": 408,
      "profile_visits": 104,
      "preview_url": "https://fb.me/1QnsymdbnDJ62YH"
    },
    {
      "name": "Ad 01 - REELS - MULTIFOCAL HOYA - BELÉM - NÃO TÁ ENXERGANDO",
      "ad_id": "120244460708210661",
      "city": "BELÉM",
      "offer": "MULTIFOCAL",
      "hook": "MULTIFOCAL",
      "status": "ATIVO",
      "spend": 7.69,
      "conversations": 0,
      "cpa": 0.0,
      "clicks": 2,
      "ctr": 0.813,
      "reach": 196,
      "impressions": 246,
      "profile_visits": 54,
      "preview_url": "https://fb.me/1TvBu8TCMEaPJuF"
    },
    {
      "name": "Ad 04 - REELS - AQUECIMENTO - BELÉM",
      "ad_id": "120244467502430661",
      "city": "BELÉM",
      "offer": "AQUECIMENTO",
      "hook": "OUTRO",
      "status": "ATIVO",
      "spend": 8.22,
      "conversations": 0,
      "cpa": 0.0,
      "clicks": 5,
      "ctr": 0.1508,
      "reach": 1870,
      "impressions": 3316,
      "profile_visits": 144,
      "preview_url": "https://fb.me/28sRac8lJbByZCh"
    },
    {
      "name": "Ad 05 - REELS - AQUECIMENTO - BELÉM — Cópia",
      "ad_id": "120244467534970661",
      "city": "BELÉM",
      "offer": "AQUECIMENTO",
      "hook": "OUTRO",
      "status": "ATIVO",
      "spend": 1.2,
      "conversations": 0,
      "cpa": 0.0,
      "clicks": 0,
      "ctr": 0.0,
      "reach": 396,
      "impressions": 484,
      "profile_visits": 24,
      "preview_url": "https://fb.me/2EiqtzhaGtksAq5"
    },
    {
      "name": "Ad 04 - REELS - AQUECIMENTO - CASTANHAL",
      "ad_id": "120244467648210661",
      "city": "CASTANHAL",
      "offer": "AQUECIMENTO",
      "hook": "OUTRO",
      "status": "ATIVO",
      "spend": 0.16,
      "conversations": 0,
      "cpa": 0.0,
      "clicks": 0,
      "ctr": 0.0,
      "reach": 68,
      "impressions": 75,
      "profile_visits": 6,
      "preview_url": "https://fb.me/24Sqk80lnFXpie9"
    },
    {
      "name": "Ad 05 - REELS - AQUECIMENTO - CASTANHAL",
      "ad_id": "120244467698500661",
      "city": "CASTANHAL",
      "offer": "AQUECIMENTO",
      "hook": "OUTRO",
      "status": "ATIVO",
      "spend": 9.5,
      "conversations": 1,
      "cpa": 9.5,
      "clicks": 10,
      "ctr": 0.2392,
      "reach": 1806,
      "impressions": 4180,
      "profile_visits": 160,
      "preview_url": "https://fb.me/qwcq1n5lc83YvvR"
    },
    {
      "name": "Ad 05 - REELS - AQUECIMENTO - ANANINDEUA",
      "ad_id": "120244467771340661",
      "city": "ANANINDEUA",
      "offer": "AQUECIMENTO",
      "hook": "OUTRO",
      "status": "ATIVO",
      "spend": 0.4,
      "conversations": 0,
      "cpa": 0.0,
      "clicks": 2,
      "ctr": 0.0163,
      "reach": 112,
      "impressions": 123,
      "profile_visits": 12,
      "preview_url": "https://fb.me/26KVDROWXBeGjM9"
    },
    {
      "name": "Ad 06 - REELS - AQUECIMENTO - ANANINDEUA",
      "ad_id": "120244467780970661",
      "city": "ANANINDEUA",
      "offer": "AQUECIMENTO",
      "hook": "OUTRO",
      "status": "ATIVO",
      "spend": 8.87,
      "conversations": 0,
      "cpa": 0.0,
      "clicks": 6,
      "ctr": 0.1982,
      "reach": 1376,
      "impressions": 3027,
      "profile_visits": 149,
      "preview_url": "https://fb.me/2jyNwM8PdKbCYKV"
    },
    {
      "name": "Ad 06 - REELS - AQUECIMENTO - CAPANEMA",
      "ad_id": "120244467808760661",
      "city": "CAPANEMA",
      "offer": "AQUECIMENTO",
      "hook": "OUTRO",
      "status": "ATIVO",
      "spend": 5.04,
      "conversations": 0,
      "cpa": 0.0,
      "clicks": 5,
      "ctr": 0.2999,
      "reach": 783,
      "impressions": 1667,
      "profile_visits": 75,
      "preview_url": "https://fb.me/1OEuJT2Jm5Kk3IM"
    },
    {
      "name": "Ad 07 - REELS - AQUECIMENTO - CAPANEMA",
      "ad_id": "120244467857610661",
      "city": "CAPANEMA",
      "offer": "AQUECIMENTO",
      "hook": "OUTRO",
      "status": "ATIVO",
      "spend": 1.29,
      "conversations": 0,
      "cpa": 0.0,
      "clicks": 0,
      "ctr": 0.0,
      "reach": 299,
      "impressions": 428,
      "profile_visits": 10,
      "preview_url": "https://fb.me/2oUff1PI7DmTjuz"
    },
    {
      "name": "Ad 08 - REELS - AQUECIMENTO - CAPANEMA",
      "ad_id": "120244467874320661",
      "city": "CAPANEMA",
      "offer": "AQUECIMENTO",
      "hook": "OUTRO",
      "status": "ATIVO",
      "spend": 2.71,
      "conversations": 0,
      "cpa": 0.0,
      "clicks": 2,
      "ctr": 0.2296,
      "reach": 543,
      "impressions": 871,
      "profile_visits": 34,
      "preview_url": "https://fb.me/2fhpbfZy3aE1uBJ"
    },
    {
      "name": "Ad 00 - REELS - DOBRO - CASTANHAL — ÓCULOS ACETATO",
      "ad_id": "120244628219770661",
      "city": "CASTANHAL",
      "offer": "EM DOBRO",
      "hook": "DOBRO",
      "status": "ATIVO",
      "spend": 15.28,
      "conversations": 2,
      "cpa": 7.64,
      "clicks": 2,
      "ctr": 0.1938,
      "reach": 857,
      "impressions": 1032,
      "profile_visits": 189,
      "preview_url": "https://fb.me/23M9n9ywGSeqB0T"
    },
    {
      "name": "Ad 01 - REELS - DOBRO - CASTANHAL —  RESULTADO EM DOBRO",
      "ad_id": "120244629429790661",
      "city": "CASTANHAL",
      "offer": "EM DOBRO",
      "hook": "DOBRO",
      "status": "ATIVO",
      "spend": 14.08,
      "conversations": 0,
      "cpa": 0.0,
      "clicks": 8,
      "ctr": 0.4788,
      "reach": 1355,
      "impressions": 1671,
      "profile_visits": 186,
      "preview_url": "https://fb.me/1PVJCYTNtGG9BaK"
    },
    {
      "name": "Ad 01 - REELS - DOBRO - CASTANHAL —  RESULTADO EM DOBRO",
      "ad_id": "120244629429800661",
      "city": "CASTANHAL",
      "offer": "EM DOBRO",
      "hook": "DOBRO",
      "status": "ATIVO",
      "spend": 14.21,
      "conversations": 2,
      "cpa": 7.11,
      "clicks": 11,
      "ctr": 0.6936,
      "reach": 1267,
      "impressions": 1586,
      "profile_visits": 188,
      "preview_url": "https://fb.me/1YEXeiP74aJ60cT"
    },
    {
      "name": "Ad 00 - REELS - DOBRO - ANANINDEUA — ÓCULOS ACETATO",
      "ad_id": "120244629444250661",
      "city": "ANANINDEUA",
      "offer": "EM DOBRO",
      "hook": "DOBRO",
      "status": "ATIVO",
      "spend": 13.62,
      "conversations": 0,
      "cpa": 0.0,
      "clicks": 7,
      "ctr": 0.0113,
      "reach": 540,
      "impressions": 620,
      "profile_visits": 141,
      "preview_url": "https://fb.me/20wMAcJpCbtYocg"
    },
    {
      "name": "Ad 00 - REELS - DOBRO - ANANINDEUA — ÓCULOS ACETATO",
      "ad_id": "120244629604740661",
      "city": "ANANINDEUA",
      "offer": "EM DOBRO",
      "hook": "DOBRO",
      "status": "ATIVO",
      "spend": 14.15,
      "conversations": 1,
      "cpa": 14.15,
      "clicks": 4,
      "ctr": 0.5571,
      "reach": 635,
      "impressions": 718,
      "profile_visits": 146,
      "preview_url": "https://fb.me/1T5mcRco8Zw90Xv"
    },
    {
      "name": "Ad 00 - REELS - DOBRO - ANANINDEUA — ÓCULOS ACETATO",
      "ad_id": "120244629604750661",
      "city": "ANANINDEUA",
      "offer": "EM DOBRO",
      "hook": "DOBRO",
      "status": "ATIVO",
      "spend": 14.0,
      "conversations": 1,
      "cpa": 14.0,
      "clicks": 2,
      "ctr": 0.3306,
      "reach": 550,
      "impressions": 605,
      "profile_visits": 132,
      "preview_url": "https://fb.me/20q7uvNdcToM57C"
    },
    {
      "name": "Ad 01 - REELS - DOBRO - ANANINDEUA —  RESULTADO EM DOBRO",
      "ad_id": "120244629604770661",
      "city": "ANANINDEUA",
      "offer": "EM DOBRO",
      "hook": "DOBRO",
      "status": "ATIVO",
      "spend": 0.58,
      "conversations": 0,
      "cpa": 0.0,
      "clicks": 0,
      "ctr": 0.0,
      "reach": 43,
      "impressions": 44,
      "profile_visits": 10,
      "preview_url": "https://fb.me/ykomwWcb3qvAmVH"
    },
    {
      "name": "Ad 01 - REELS - DOBRO - BELÉM —  RESULTADO EM DOBRO",
      "ad_id": "120244629769080661",
      "city": "BELÉM",
      "offer": "EM DOBRO",
      "hook": "DOBRO",
      "status": "ATIVO",
      "spend": 11.7,
      "conversations": 2,
      "cpa": 5.85,
      "clicks": 8,
      "ctr": 0.0104,
      "reach": 696,
      "impressions": 772,
      "profile_visits": 122,
      "preview_url": "https://fb.me/2hTpqdPHu8M5tM7"
    },
    {
      "name": "Ad 00 - REELS - DOBRO - BELÉM — ÓCULOS ACETATO",
      "ad_id": "120244629769090661",
      "city": "BELÉM",
      "offer": "EM DOBRO",
      "hook": "DOBRO",
      "status": "ATIVO",
      "spend": 1.24,
      "conversations": 0,
      "cpa": 0.0,
      "clicks": 1,
      "ctr": 0.0208,
      "reach": 47,
      "impressions": 48,
      "profile_visits": 13,
      "preview_url": "https://fb.me/1TJ57ZFFeTb4n50"
    },
    {
      "name": "Ad 01 - REELS - DOBRO - BELÉM —  RESULTADO EM DOBRO",
      "ad_id": "120244631058360661",
      "city": "BELÉM",
      "offer": "EM DOBRO",
      "hook": "DOBRO",
      "status": "ATIVO",
      "spend": 13.08,
      "conversations": 0,
      "cpa": 0.0,
      "clicks": 5,
      "ctr": 0.7862,
      "reach": 552,
      "impressions": 636,
      "profile_visits": 104,
      "preview_url": "https://fb.me/1W953IxpVse5tfq"
    },
    {
      "name": "Ad 00 - REELS - DOBRO - BELÉM — ÓCULOS ACETATO",
      "ad_id": "120244631058390661",
      "city": "BELÉM",
      "offer": "EM DOBRO",
      "hook": "DOBRO",
      "status": "ATIVO",
      "spend": 1.11,
      "conversations": 0,
      "cpa": 0.0,
      "clicks": 0,
      "ctr": 0.0,
      "reach": 36,
      "impressions": 36,
      "profile_visits": 10,
      "preview_url": "https://fb.me/1U1sg0zh8qplveK"
    },
    {
      "name": "Ad 00 - REELS - DOBRO - BELÉM — ÓCULOS ACETATO",
      "ad_id": "120244631058400661",
      "city": "BELÉM",
      "offer": "EM DOBRO",
      "hook": "DOBRO",
      "status": "ATIVO",
      "spend": 16.53,
      "conversations": 2,
      "cpa": 8.27,
      "clicks": 6,
      "ctr": 0.0106,
      "reach": 504,
      "impressions": 567,
      "profile_visits": 166,
      "preview_url": "https://fb.me/25nOBom1U0OD3oL"
    },
    {
      "name": "Ad 00 - REELS - R$1,00 - CASTANHAL — ALGUÉM ME ELOGIA",
      "ad_id": "120244631209520661",
      "city": "CASTANHAL",
      "offer": "R$ 1,00",
      "hook": "OUTRO",
      "status": "ATIVO",
      "spend": 8.63,
      "conversations": 0,
      "cpa": 0.0,
      "clicks": 1,
      "ctr": 0.1531,
      "reach": 539,
      "impressions": 653,
      "profile_visits": 132,
      "preview_url": "https://fb.me/20DIybSDgFIrKRs"
    },
    {
      "name": "Ad 01 - REELS - R$1,00 - ANANINDEUA —  MODELO HEXAGONAL",
      "ad_id": "120244631209620661",
      "city": "ANANINDEUA",
      "offer": "R$ 1,00",
      "hook": "OUTRO",
      "status": "ATIVO",
      "spend": 14.31,
      "conversations": 1,
      "cpa": 14.31,
      "clicks": 9,
      "ctr": 0.9137,
      "reach": 895,
      "impressions": 985,
      "profile_visits": 206,
      "preview_url": "https://fb.me/2gSLP8PrUmO0UD7"
    },
    {
      "name": "Ad 00 - REELS - R$1,00 - ANANINDEUA — ALGUÉM ME ELOGIA",
      "ad_id": "120244631209630661",
      "city": "ANANINDEUA",
      "offer": "R$ 1,00",
      "hook": "OUTRO",
      "status": "ATIVO",
      "spend": 0.55,
      "conversations": 0,
      "cpa": 0.0,
      "clicks": 0,
      "ctr": 0.0,
      "reach": 48,
      "impressions": 51,
      "profile_visits": 8,
      "preview_url": "https://fb.me/2wFkHcOsJyWW9e9"
    },
    {
      "name": "Ad 01 - REELS - R$1,00 - BELÉM — ALGUÉM ME ELOGIA",
      "ad_id": "120244631209700661",
      "city": "BELÉM",
      "offer": "R$ 1,00",
      "hook": "OUTRO",
      "status": "ATIVO",
      "spend": 14.8,
      "conversations": 1,
      "cpa": 14.8,
      "clicks": 5,
      "ctr": 0.7418,
      "reach": 642,
      "impressions": 674,
      "profile_visits": 226,
      "preview_url": "https://fb.me/248yNkRNtN9oDmG"
    }
  ]
}